g9/__init__.py
g9/ExampleAgent.py
g9-0.0.1.dev1.dist-info/METADATA
g9-0.0.1.dev1.dist-info/WHEEL
g9-0.0.1.dev1.dist-info/RECORD
